samdown/__init__.py
samdown/block.py
samdown/raw.py
samdown-0.2.0.dist-info/DESCRIPTION.rst
samdown-0.2.0.dist-info/METADATA
samdown-0.2.0.dist-info/RECORD
samdown-0.2.0.dist-info/WHEEL
samdown-0.2.0.dist-info/metadata.json
samdown-0.2.0.dist-info/top_level.txt
